librenms_mcp/__init__.py
librenms_mcp/librenms_client.py
librenms_mcp/librenms_middlewares.py
librenms_mcp/librenms_tools.py
librenms_mcp/models.py
librenms_mcp/sentry_init.py
librenms_mcp/server.py
librenms_mcp/utils.py
librenms_mcp-1.5.0.dist-info/METADATA
librenms_mcp-1.5.0.dist-info/WHEEL
librenms_mcp-1.5.0.dist-info/entry_points.txt
librenms_mcp-1.5.0.dist-info/licenses/LICENSE
librenms_mcp-1.5.0.dist-info/RECORD
